grocker_test_project-3.0.1.dist-info/DESCRIPTION.rst
grocker_test_project-3.0.1.dist-info/METADATA
grocker_test_project-3.0.1.dist-info/RECORD
grocker_test_project-3.0.1.dist-info/WHEEL
grocker_test_project-3.0.1.dist-info/entry_points.txt
grocker_test_project-3.0.1.dist-info/metadata.json
grocker_test_project-3.0.1.dist-info/top_level.txt
grocker_test_project-3.0.1.dist-info/zip-safe
gtp/__init__.py
gtp/__main__.py
