Metadata-Version: 2.0
Name: grocker-test-project
Version: 3.0.1
Summary: Test project for Grocker
Home-page: http://github.com/polyconseil/grocker
Author: Polyconseil
Author-email: opensource+grocker@polyconseil.fr
License: UNKNOWN
Platform: UNKNOWN
Requires-Dist: Pillow
Requires-Dist: qrcode
Provides-Extra: pep8
Requires-Dist: pep8 (==1.7.0); extra == 'pep8'
